{"variables":[],"info":{"name":"","_postman_id":"cc508555-d3dc-4c39-b18d-923bf1e2bb8b","description":"","schema":"https:\/\/schema.getpostman.com\/json\/collection\/v2.0.0\/collection.json"},"item":[{"name":"Group Management\n\nAPIs for managing groups","description":"","item":[{"name":"Get group items","request":{"url":"http:\/\/groscery.test\/api\/groups\/items","method":"GET","body":{"mode":"formdata","formdata":[]},"description":"Get all the group's items","response":[]}}]},{"name":"Item Management\n\nAPIs for managing items","description":"","item":[{"name":"Add new item","request":{"url":"http:\/\/groscery.test\/api\/items\/add","method":"POST","body":{"mode":"formdata","formdata":[]},"description":"","response":[]}},{"name":"Sets given item out of stock","request":{"url":"http:\/\/groscery.test\/api\/items\/item.out-of-stock\/{item_id}","method":"POST","body":{"mode":"formdata","formdata":[]},"description":"","response":[]}},{"name":"Sets given item in stock","request":{"url":"http:\/\/groscery.test\/api\/items\/item.in-stock\/{item_id}","method":"POST","body":{"mode":"formdata","formdata":[]},"description":"","response":[]}}]},{"name":"User Management\n\nAPIs for managing users","description":"","item":[{"name":"Login user","request":{"url":"http:\/\/groscery.test\/api\/login","method":"POST","body":{"mode":"formdata","formdata":[{"key":"email","value":"1Oe4NT9IacpAnf2E","type":"text","enabled":true},{"key":"password","value":"v5VroN4i9y27CyQw","type":"text","enabled":true}]},"description":"","response":[]}},{"name":"Register new user","request":{"url":"http:\/\/groscery.test\/api\/register","method":"POST","body":{"mode":"formdata","formdata":[{"key":"name","value":"ju8gUSenE99mGPVC","type":"text","enabled":true},{"key":"email","value":"DpVftU1ez6VAvGAW","type":"text","enabled":true},{"key":"password","value":"HXtBG7t0OymTlZXq","type":"text","enabled":true},{"key":"c_password","value":"HghbzXHvAxjt3S7a","type":"text","enabled":true}]},"description":"","response":[]}},{"name":"User details","request":{"url":"http:\/\/groscery.test\/api\/details","method":"POST","body":{"mode":"formdata","formdata":[]},"description":"Returns basic user information","response":[]}},{"name":"Logout user","request":{"url":"http:\/\/groscery.test\/api\/logout","method":"POST","body":{"mode":"formdata","formdata":[]},"description":"","response":[]}},{"name":"User items","request":{"url":"http:\/\/groscery.test\/api\/users\/items","method":"GET","body":{"mode":"formdata","formdata":[]},"description":"Returns a user's items","response":[]}}]}]}